et_engine_core/__init__.py
et_engine_core/batches.py
et_engine_core/filesystems.py
et_engine_core/jobs.py
et_engine_core/tools.py
et_engine_core-0.0.1.dist-info/LICENSE
et_engine_core-0.0.1.dist-info/METADATA
et_engine_core-0.0.1.dist-info/WHEEL
et_engine_core-0.0.1.dist-info/top_level.txt
et_engine_core-0.0.1.dist-info/RECORD
