Metadata-Version: 2.1
Name: et_engine_core
Version: 0.0.1
Summary: Low-level interface for the ET Engine
Author-email: "Exploration Technologies, Inc." <info@exploretech.ai>
License: 
Requires-Python: >=3.11.9
License-File: LICENSE
